alu.v
module alu 
# (parameter [3:0] ALUOP_AND = 4'b0000,
    ALUOP_OR = 4'b0001,
    ALUOP_ADD = 4'b0010,
    ALUOP_SUB = 4'b0110,
    ALUOP_COM = 4'b0111,
    ALUOP_SHIFT_RIGHT = 4'b1000,
    ALUOP_SHIFT_LEFT = 4'b1001,
    ALUOP_ARITHM_RIGHT = 4'b1010,
    ALUOP_XOR = 4'b1101)

(output reg zero,
output reg  signed [31:0] result,
input signed  [31:0] op1,
input signed  [31:0] op2,
input wire [3:0] alu_op
);
always @ (*)
begin
case (alu_op)
ALUOP_AND : result = op1 & op2;
ALUOP_OR : result = op1 | op2;
ALUOP_ADD : result = op1 + op2;
ALUOP_SUB : result = op1 - op2;
ALUOP_COM : result = op1 < op2;
ALUOP_SHIFT_RIGHT : result = op1>>op2[4:0];
ALUOP_SHIFT_LEFT : result = op1<<op2[4:0];
ALUOP_ARITHM_RIGHT : result = $unsigned(op1>>>op2[4:0]);
ALUOP_XOR : result = op1^op2;
default : result = 32'b0;
endcase
zero = (result==32'b0) ? 1'b1 : 1'b0;
end
endmodule

decoder.v


module decoder (output wire [3:0] F,
input wire A,B,C);
wire An,Bn,Cn,Dn,En,Fn,Gn,Hn,In,Jn,m0,m1,m2,m3,m4,m5;
//1st bit (alu_op[0])
not U0 (An,A);
xor U1(Bn,B,C);
and U2(m0,An,B);
and U3(m1,A,Bn);
or U4(F[0],m0,m1);

//2nd bit (alu_op[1])
and U5 (Cn,A,B);
not U6(Dn,B);
not U7(En,C);
and U8(m2,Dn,En);
or U9(F[1],m2,Cn);

//3rd bit (alu_op[2])
and U10(Fn,A,B);
xor U11(Gn,A,B);
not U12(Hn,C);
or U13(m3,Fn,Gn);
and U14(F[2],m3,Hn);

//4th bit (alu_op[3])
not U15(In,A);
xnor U16(Jn,A,C);
and U17(m4,In,C);
or U18(m5,m4,Jn);
and U19(F[3],m5,B);

endmodule

calc.v
`include "alu.v"
`include "decoder.v"
module calc (output reg [15:0] led,
input clk,btnc,btnl,btnu,btnr,btnd,
input wire signed [15:0] sw);
reg  signed [15:0] accumulator;
reg signed [31:0] acc_sign;
reg signed [31:0] sw_sign;
wire  signed [31:0] n0;
wire [3:0] n1;


always @(accumulator or sw)
begin 
    acc_sign <= {{16{accumulator[15]}},accumulator};
    sw_sign <= {{16{sw[15]}},sw};
end

decoder U0 (.F(n1), .A(btnr), .B(btnl), .C(btnc));

alu U1 (.result(n0), 
.op1(acc_sign), 
.op2(sw_sign),
.alu_op(n1));



always @ (posedge clk or posedge btnu)
begin
if(btnu) begin
    accumulator = 0;
    led=0;
end
else if(btnd) begin
    accumulator = n0[15:0];
    led = accumulator;
end
else begin
    accumulator <= accumulator;
    //led<=led; 
end

end

endmodule

calc_tb.v
`include "calc.v"
`timescale 1ns/1ns
module calc_tb;
reg clk,btnc,btnl,btnu,btnr,btnd;
reg signed [15:0] sw;
wire [15:0] led;

calc DUT(led,clk,btnc,btnl,btnu,btnr,btnd,sw);


    

initial begin
$dumpfile("calc_tb.vcd");
$dumpvars(0,calc_tb);


clk=1'b0;
btnd=0;
btnu = 1'b0;

btnd=1;
btnl=0;
btnc=0;
btnr=0;
sw=16'h0000;
#10 btnu=1;



#10;
btnd=1;
btnu=0;
btnl=0;
btnc=1;
btnr=1;
sw=16'h1234;


#10;
btnl=0;
btnc=1;
btnr=0;
sw=16'h0ff0;

#10;
btnl=0;
btnc=0;
btnr=0;
sw=16'h324f;

#10;
btnl=0;
btnc=0;
btnr=1;
sw=16'h2d31;

#10;
btnl=1;
btnc=0;
btnr=0;
sw=16'hffff;

#10;
btnl=1;
btnc=0;
btnr=1;
sw=16'h7346;

#10;
btnl=1;
btnc=1;
btnr=0;
sw=16'h0004;

#10;
btnl=1;
btnc=1;
btnr=1;
sw=16'h0004;

#10;
btnl=1;
btnc=0;
btnr=1;
sw=16'hffff;

$display("Test complete");
#30;
$finish();

end

always begin 
        #5 clk=~clk;
    end
endmodule

calc_tb.vcd
$date
	Sat Dec 23 19:50:52 2023
$end
$version
	Icarus Verilog
$end
$timescale
	1ns
$end
$scope module calc_tb $end
$var wire 16 ! led [15:0] $end
$var reg 1 " btnc $end
$var reg 1 # btnd $end
$var reg 1 $ btnl $end
$var reg 1 % btnr $end
$var reg 1 & btnu $end
$var reg 1 ' clk $end
$var reg 16 ( sw [15:0] $end
$scope module DUT $end
$var wire 1 " btnc $end
$var wire 1 # btnd $end
$var wire 1 $ btnl $end
$var wire 1 % btnr $end
$var wire 1 & btnu $end
$var wire 1 ' clk $end
$var wire 16 ) sw [15:0] $end
$var wire 4 * n1 [3:0] $end
$var wire 32 + n0 [31:0] $end
$var reg 32 , acc_sign [31:0] $end
$var reg 16 - accumulator [15:0] $end
$var reg 16 . led [15:0] $end
$var reg 32 / sw_sign [31:0] $end
$scope module U0 $end
$var wire 1 % A $end
$var wire 1 0 An $end
$var wire 1 $ B $end
$var wire 1 1 Bn $end
$var wire 1 " C $end
$var wire 1 2 Cn $end
$var wire 1 3 Dn $end
$var wire 1 4 En $end
$var wire 1 5 Fn $end
$var wire 1 6 Gn $end
$var wire 1 7 Hn $end
$var wire 1 8 In $end
$var wire 1 9 Jn $end
$var wire 1 : m0 $end
$var wire 1 ; m1 $end
$var wire 1 < m2 $end
$var wire 1 = m3 $end
$var wire 1 > m4 $end
$var wire 1 ? m5 $end
$var wire 4 @ F [3:0] $end
$upscope $end
$scope module U1 $end
$var wire 4 A alu_op [3:0] $end
$var wire 32 B op1 [31:0] $end
$var wire 32 C op2 [31:0] $end
$var parameter 4 D ALUOP_ADD $end
$var parameter 4 E ALUOP_AND $end
$var parameter 4 F ALUOP_ARITHM_RIGHT $end
$var parameter 4 G ALUOP_COM $end
$var parameter 4 H ALUOP_OR $end
$var parameter 4 I ALUOP_SHIFT_LEFT $end
$var parameter 4 J ALUOP_SHIFT_RIGHT $end
$var parameter 4 K ALUOP_SUB $end
$var parameter 4 L ALUOP_XOR $end
$var reg 32 M result [31:0] $end
$var reg 1 N zero $end
$upscope $end
$upscope $end
$upscope $end
$enddefinitions $end
$comment Show the parameter values. $end
$dumpall
b1101 L
b110 K
b1000 J
b1001 I
b1 H
b111 G
b1010 F
b0 E
b10 D
$end
#0
$dumpvars
xN
bx M
b0 C
bx B
b10 A
b10 @
1?
0>
0=
1<
0;
0:
19
18
17
06
05
14
13
02
01
10
b0 /
bx .
bx -
bx ,
bx +
b10 *
b0 )
b0 (
0'
0&
0%
0$
1#
0"
bx !
$end
#5
1'
#10
1N
b0 +
b0 M
b0 ,
b0 B
b0 !
b0 .
b0 -
0'
1&
#15
1'
#20
0N
b1001000110100 +
b1001000110100 M
b1001000110100 /
b1001000110100 C
b1 *
b1 @
b1 A
1=
0<
00
1;
16
08
11
04
07
0>
0'
b1001000110100 (
b1001000110100 )
1%
1"
0&
#25
b1001000110100 ,
b1001000110100 B
b1001000110100 !
b1001000110100 .
b1001000110100 -
1'
#30
b1000110000 +
b1000110000 M
b111111110000 /
b111111110000 C
b0 *
b0 @
b0 A
0=
1>
1?
10
0;
06
18
09
0'
b111111110000 (
b111111110000 )
0%
#35
b1000110000 ,
b1000110000 B
b1000110000 !
b1000110000 .
b1000110000 -
1'
#40
b11001001001111 /
b11001001001111 C
b11010001111111 +
b11010001111111 M
b10 *
b10 @
b10 A
1<
01
14
17
19
0>
0'
b11001001001111 (
b11001001001111 )
0"
#45
b110011011001110 +
b110011011001110 M
b11010001111111 ,
b11010001111111 B
b11010001111111 !
b11010001111111 .
b11010001111111 -
1'
#50
b10110100110001 /
b10110100110001 C
b11101001110 +
b11101001110 M
b110 *
b110 @
b110 A
1=
0?
00
16
08
09
0'
b10110100110001 (
b10110100110001 )
1%
#55
b11111111111111111101101000011101 +
b11111111111111111101101000011101 M
b11101001110 ,
b11101001110 B
b11101001110 !
b11101001110 .
b11101001110 -
1'
#60
b11111111111111111111111111111111 /
b11111111111111111111111111111111 C
b11111111111111111111100010110001 +
b11111111111111111111100010110001 M
b1101 *
b1101 @
b1101 A
1:
1?
0<
10
18
19
11
03
0'
b1111111111111111 (
b1111111111111111 )
0%
1$
#65
b11101001110 +
b11101001110 M
b11111111111111111111100010110001 ,
b11111111111111111111100010110001 B
b1111100010110001 !
b1111100010110001 .
b1111100010110001 -
1'
#70
b111001101000110 /
b111001101000110 C
b1 +
b1 M
0:
b111 *
b111 @
b111 A
0?
00
1;
12
15
06
08
09
0'
b111001101000110 (
b111001101000110 )
1%
#75
b1 ,
b1 B
b1 !
b1 .
b1 -
1'
#80
b100 /
b100 C
1?
0N
b10000 +
b10000 M
1:
1>
b1001 *
b1001 @
b1001 A
10
0;
02
05
16
18
01
04
07
0'
b100 (
b100 )
0%
1"
#85
b100000000 +
b100000000 M
b10000 ,
b10000 B
b10000 !
b10000 .
b10000 -
1'
#90
0N
b1 +
b1 M
0:
b1010 *
b1010 @
b1010 A
0>
00
12
15
06
08
19
0'
1%
#95
1N
b0 +
b0 M
b1 ,
b1 B
b1 !
b1 .
b1 -
1'
#100
b11111111111111111111111111111111 /
b11111111111111111111111111111111 C
1N
b0 +
b0 M
1;
b111 *
b111 @
b111 A
0?
11
14
17
09
0'
b1111111111111111 (
b1111111111111111 )
0"
